pytest_trytond/__init__.py
pytest_trytond/plugin.py
pytest_trytond/tools.py
pytest_trytond-0.1.0.dist-info/METADATA
pytest_trytond-0.1.0.dist-info/WHEEL
pytest_trytond-0.1.0.dist-info/entry_points.txt
pytest_trytond-0.1.0.dist-info/top_level.txt
pytest_trytond-0.1.0.dist-info/RECORD
