Metadata-Version: 2.1
Name: pytest-trytond
Version: 0.1.0
Summary: Pytest plugin for the Tryton server framework
Home-page: https://github.com/calidae/pytest-trytond
Author: Calidae
Author-email: dev@calidae.com
License: GNU General Public License v3 or later (GPLv3+)
Platform: any
Classifier: Development Status :: 4 - Beta
Classifier: Environment :: Plugins
Classifier: Framework :: Pytest
Classifier: Framework :: Tryton
Classifier: Intended Audience :: Developers
Classifier: License :: OSI Approved :: GNU General Public License v3 or later (GPLv3+)
Classifier: Operating System :: OS Independent
Classifier: Programming Language :: Python :: 3
Classifier: Programming Language :: Python :: 3 :: Only
Classifier: Programming Language :: Python :: 3.8
Classifier: Programming Language :: Python :: 3.9
Classifier: Programming Language :: Python :: 3.10
Classifier: Programming Language :: Python :: 3.11
Classifier: Topic :: Software Development :: Testing :: Unit
Requires-Python: >=3.8
Requires-Dist: pytest (>=5)
Requires-Dist: trytond
